.gitignore
MANIFEST.in
README.md
hifibgc.LICENSE
setup.py
hifibgc/__init__.py
hifibgc/__main__.py
hifibgc/cli_utils.py
hifibgc/hifibgc.CITATION
hifibgc/hifibgc.VERSION
hifibgc.egg-info/PKG-INFO
hifibgc.egg-info/SOURCES.txt
hifibgc.egg-info/dependency_links.txt
hifibgc.egg-info/entry_points.txt
hifibgc.egg-info/requires.txt
hifibgc.egg-info/top_level.txt
hifibgc/config/config.yaml
hifibgc/test_data/test_data_sampled.fastq
hifibgc/workflow/hifibgc.smk
hifibgc/workflow/install.smk
hifibgc/workflow/envs/antismash_v7.yml
hifibgc/workflow/envs/bigscape.yml
hifibgc/workflow/envs/canu.yml
hifibgc/workflow/envs/flye.yml
hifibgc/workflow/envs/hifiasm_meta.yml
hifibgc/workflow/envs/mapping.yml
hifibgc/workflow/envs/r_complexupset.yml
hifibgc/workflow/scripts/generate_final_outputs.py
hifibgc/workflow/scripts/prepare_input_for_bigscape.py
hifibgc/workflow/scripts/prepare_input_for_upsetplot.py
hifibgc/workflow/scripts/upsetplot.R