Metadata-Version: 2.1
Name: hifibgc
Version: 0.1.14
Summary: Detect Biosynthetic Gene Clusters (BGCs) in HiFi metagenomic data
Home-page: 
Author: Amit Yadav
Author-email: ayamitjyoti12@gmail.com
Requires-Python: >=3.9,<3.12
